chunkyp/__init__.py
chunkyp/__main__.py
chunkyp/pipeline.py
chunkyp/utils.py
chunkyp/tests/__init__.py
chunkyp/tests/test_pipeline.py
chunkyp-0.0.2.dist-info/LICENSE
chunkyp-0.0.2.dist-info/METADATA
chunkyp-0.0.2.dist-info/WHEEL
chunkyp-0.0.2.dist-info/top_level.txt
chunkyp-0.0.2.dist-info/RECORD
