Metadata-Version: 2.1
Name: chunkyp
Version: 0.0.2
Summary: Ray-based preprocesisng pipeline.
Home-page: https://github.com/neophocion/chunkyp
Author: Neo Phocion
Author-email: neophocion@protonmail.com
License: apache-2.0
Download-URL: https://github.com/neophocion/chunkyp/releases
Project-URL: Repo, https://github.com/neophocion/chunkyp
Keywords: ray,preprocessing,nlp,cleaning,workflow
Platform: UNKNOWN
Classifier: Development Status :: 3 - Alpha
Classifier: Intended Audience :: Developers
Classifier: Topic :: Text Processing
Classifier: Topic :: Scientific/Engineering
Classifier: License :: OSI Approved :: Apache Software License
Classifier: Programming Language :: Python :: 3
Classifier: Programming Language :: Python :: 3.5
Classifier: Programming Language :: Python :: 3.6
Classifier: Programming Language :: Python :: 3.7
Classifier: Programming Language :: Python :: 3.8
Requires-Python: >=3.5, <4
Requires-Dist: ray (>=0.8.6)
Requires-Dist: psutil (>=5.7.0)
Provides-Extra: dev
Requires-Dist: pytest ; extra == 'dev'
Provides-Extra: test
